pelican/plugins/precompress/__init__.py
pelican/plugins/precompress/compat.py
pelican_precompress-2.4.0.dist-info/METADATA
pelican_precompress-2.4.0.dist-info/WHEEL
pelican_precompress-2.4.0.dist-info/licenses/LICENSE.txt
pelican_precompress-2.4.0.dist-info/RECORD
