Metadata-Version: 2.4
Name: pelican-precompress
Version: 2.4.0
Summary: Pre-compress your Pelican site using gzip, brotli, zstandard, and zopfli!
License-Expression: MIT
License-File: LICENSE.txt
Keywords: pelican,plugin,gzip,brotli,zstandard,zstd,zopfli
Author: Kurt McKee
Author-email: contactme@kurtmckee.org
Requires-Python: >=3.10
Classifier: Development Status :: 5 - Production/Stable
Classifier: Framework :: Pelican :: Plugins
Classifier: License :: OSI Approved :: MIT License
Classifier: Programming Language :: Python :: 3
Provides-Extra: brotli
Provides-Extra: zopfli
Provides-Extra: zstandard
Requires-Dist: backports.zstd ; (python_version < "3.14") and (extra == "zstandard")
Requires-Dist: brotli ; extra == "brotli"
Requires-Dist: pelican-granular-signals (>=1.0.0,<2.0.0)
Requires-Dist: zopfli ; extra == "zopfli"
Project-URL: Changelog, https://github.com/kurtmckee/pelican-precompress/blob/main/CHANGELOG.rst
Project-URL: Donate via GitHub, https://github.com/sponsors/kurtmckee
Project-URL: Donate via Ko-Fi, https://ko-fi.com/kurtmckee
Project-URL: Source, https://github.com/kurtmckee/pelican-precompress
